ipfabric_infoblox/__init__.py
ipfabric_infoblox/cli.py
ipfabric_infoblox/config/__init__.py
ipfabric_infoblox/config/config.py
ipfabric_infoblox/config/infoblox.py
ipfabric_infoblox/config/ipfabric.py
ipfabric_infoblox/config/models.py
ipfabric_infoblox/config/network_view.py
ipfabric_infoblox/config/vrf.py
ipfabric_infoblox/frontend/frontend.py
ipfabric_infoblox/infoblox/__init__.py
ipfabric_infoblox/infoblox/ib_validate.py
ipfabric_infoblox/infoblox/infoblox.py
ipfabric_infoblox/infoblox/models.py
ipfabric_infoblox/ipf_models/__init__.py
ipfabric_infoblox/ipf_models/managed_ip.py
ipfabric_infoblox/ipf_models/managed_networks.py
ipfabric_infoblox/sync/__init__.py
ipfabric_infoblox/sync/ip_sync.py
ipfabric_infoblox/sync/network_sync.py
ipfabric_infoblox/sync/sync.py
ipfabric_infoblox-0.2.8.dist-info/METADATA
ipfabric_infoblox-0.2.8.dist-info/WHEEL
ipfabric_infoblox-0.2.8.dist-info/entry_points.txt
ipfabric_infoblox-0.2.8.dist-info/licenses/LICENSE
ipfabric_infoblox-0.2.8.dist-info/RECORD
