Metadata-Version: 2.4
Name: ipfabric-infoblox
Version: 0.2.8
Summary: IP Fabric Infoblox Integration
License: MIT
License-File: LICENSE
Keywords: ipfabric,ip-fabric,infoblox,nios
Author: Justin Jeffery
Author-email: justin.jeffery@ipfabric.io
Requires-Python: >=3.10,<4.0
Classifier: License :: OSI Approved :: MIT License
Classifier: Programming Language :: Python :: 3
Classifier: Programming Language :: Python :: 3.10
Classifier: Programming Language :: Python :: 3.11
Classifier: Programming Language :: Python :: 3.12
Classifier: Programming Language :: Python :: 3.13
Classifier: Programming Language :: Python :: 3.14
Provides-Extra: streamlit
Requires-Dist: click (<8.1.7)
Requires-Dist: httpx (>=0.28.1,<0.29.0)
Requires-Dist: invoke (>=2.2.0,<3.0.0)
Requires-Dist: ipfabric (>=7.0.0,<8.0.0)
Requires-Dist: ipfabric-extensions (>=0.5.10,<0.6.0)
Requires-Dist: macaddress (>=2.0.2,<3.0.0)
Requires-Dist: pydantic (>=2.8.2,<3.0.0)
Requires-Dist: pydantic-settings (>=2.4.0,<3.0.0)
Requires-Dist: pytricia (>=1.0.2,<2.0.0)
Requires-Dist: pyyaml (>=6.0.2,<7.0.0)
Requires-Dist: requests (>=2.32.3,<3.0.0)
Requires-Dist: rich (>=13.9.3,<14.0.0)
Requires-Dist: streamlit (>=1.41.1,<2.0.0) ; extra == "streamlit"
Requires-Dist: tqdm (>=4.66.6,<5.0.0)
Requires-Dist: typer (>=0.12.5,<0.13.0)
Project-URL: Changelog, https://gitlab.com/ip-fabric/integrations/ipfabric-infoblox/-/blob/main/CHANGELOG.md
Project-URL: Documentation, https://docs.ipfabric.io/main/integrations/infoblox/
Project-URL: Homepage, https://ipfabric.io/
Project-URL: Repository, https://gitlab.com/ip-fabric/integrations/ipfabric-infoblox
Project-URL: Support, https://gitlab.com/ip-fabric/integrations/ipfabric-infoblox/-/issues
